agent_trail/__init__.py
agent_trail/module.py
agent_trail-0.1.0.dist-info/licenses/LICENSE
agent_trail-0.1.0.dist-info/METADATA
agent_trail-0.1.0.dist-info/WHEEL
agent_trail-0.1.0.dist-info/top_level.txt
agent_trail-0.1.0.dist-info/RECORD
