Metadata-Version: 2.4
Name: agent_trail
Version: 0.1.0
Summary: Short description
Author-email: Xia Hua <xia@traceforce.ai>
License: MIT
Requires-Python: >=3.7
License-File: LICENSE
Dynamic: license-file
